b3alien/__init__.py
b3alien/b3cube/__init__.py
b3alien/b3cube/b3cube.py
b3alien/griis/__init__.py
b3alien/griis/griis.py
b3alien/simulation/__init__.py
b3alien/simulation/simulation.py
b3alien/utils/__init__.py
b3alien/utils/geo.py
b3alien/utils/runtime.py
b3alien/visualisation/__init__.py
b3alien/visualisation/b3gee.py
b3alien/visualisation/visualisation.py
b3alien-0.2.2.dist-info/licenses/LICENSE
b3alien-0.2.2.dist-info/METADATA
b3alien-0.2.2.dist-info/WHEEL
b3alien-0.2.2.dist-info/top_level.txt
b3alien-0.2.2.dist-info/RECORD
