Metadata-Version: 2.4
Name: b3alien
Version: 0.2.2
Summary: Calculating the CBD target 6.1 indicator from occurrence cubes
Author-email: Maarten Trekels <maarten.trekels@plantentuinmeise.be>
License: MIT
Project-URL: homepage, https://github.com/mtrekels/b3alien
Project-URL: repository, https://github.com/mtrekels/b3alien
Project-URL: documentation, https://b3alien.readthedocs.io/
Requires-Python: >=3.10
License-File: LICENSE
Requires-Dist: dask
Requires-Dist: earthengine-api
Requires-Dist: ee
Requires-Dist: folium
Requires-Dist: gcsfs
Requires-Dist: geemap
Requires-Dist: geopandas>=1.0.1
Requires-Dist: ipython
Requires-Dist: matplotlib
Requires-Dist: numpy
Requires-Dist: pandas
Requires-Dist: pillow
Requires-Dist: pyarrow
Requires-Dist: scipy
Requires-Dist: shapely
Requires-Dist: sparse
Requires-Dist: tdqm
Requires-Dist: xarray
Requires-Dist: coldp
Provides-Extra: dev
Requires-Dist: pytest; extra == "dev"
Requires-Dist: flake8; extra == "dev"
Dynamic: license-file
